jiant/__init__.py
jiant/ext/__init__.py
jiant/ext/allennlp.py
jiant/ext/radam.py
jiant/proj/__init__.py
jiant/proj/main/__init__.py
jiant/proj/main/export_model.py
jiant/proj/main/metarunner.py
jiant/proj/main/preprocessing.py
jiant/proj/main/runner.py
jiant/proj/main/runscript.py
jiant/proj/main/tokenize_and_cache.py
jiant/proj/main/write_task_configs.py
jiant/proj/main/components/__init__.py
jiant/proj/main/components/container_setup.py
jiant/proj/main/components/evaluate.py
jiant/proj/main/components/outputs.py
jiant/proj/main/components/task_sampler.py
jiant/proj/main/components/write_configs.py
jiant/proj/main/modeling/__init__.py
jiant/proj/main/modeling/heads.py
jiant/proj/main/modeling/model_setup.py
jiant/proj/main/modeling/primary.py
jiant/proj/main/modeling/taskmodels.py
jiant/proj/main/scripts/__init__.py
jiant/proj/main/scripts/configurator.py
jiant/proj/simple/__init__.py
jiant/proj/simple/runscript.py
jiant/scripts/__init__.py
jiant/scripts/benchmarks/__init__.py
jiant/scripts/benchmarks/benchmark_submission_formatter.py
jiant/scripts/benchmarks/benchmarks.py
jiant/scripts/download_data/__init__.py
jiant/scripts/download_data/constants.py
jiant/scripts/download_data/runscript.py
jiant/scripts/download_data/utils.py
jiant/scripts/download_data/dl_datasets/__init__.py
jiant/scripts/download_data/dl_datasets/files_tasks.py
jiant/scripts/download_data/dl_datasets/hf_datasets_tasks.py
jiant/scripts/download_data/dl_datasets/xtreme.py
jiant/scripts/preproc/__init__.py
jiant/scripts/preproc/export_glue_data.py
jiant/shared/__init__.py
jiant/shared/caching.py
jiant/shared/constants.py
jiant/shared/distributed.py
jiant/shared/initialization.py
jiant/shared/metarunner.py
jiant/shared/model_resolution.py
jiant/shared/model_setup.py
jiant/shared/runner.py
jiant/tasks/__init__.py
jiant/tasks/constants.py
jiant/tasks/core.py
jiant/tasks/retrieval.py
jiant/tasks/utils.py
jiant/tasks/evaluate/__init__.py
jiant/tasks/evaluate/core.py
jiant/tasks/lib/__init__.py
jiant-2.2.0.dist-info/LICENSE
jiant-2.2.0.dist-info/METADATA
jiant-2.2.0.dist-info/WHEEL
jiant-2.2.0.dist-info/top_level.txt
jiant-2.2.0.dist-info/RECORD
