Metadata-Version: 2.1
Name: jiant
Version: 2.2.0
Summary: State-of-the-art Natural Language Processing toolkit for multi-task and transfer learning built on PyTorch.
Home-page: https://github.com/nyu-mll/jiant
Author: NYU Machine Learning for Language Group
Author-email: bowman@nyu.edu
License: MIT
Keywords: NLP deep learning transformer pytorch tensorflow BERT GPT GPT-2 google nyu datasets
Platform: UNKNOWN
Classifier: Development Status :: 4 - Beta
Classifier: Intended Audience :: Developers
Classifier: Intended Audience :: Education
Classifier: Intended Audience :: Science/Research
Classifier: License :: OSI Approved :: MIT License
Classifier: Operating System :: OS Independent
Classifier: Programming Language :: Python :: 3
Classifier: Programming Language :: Python :: 3.6
Classifier: Programming Language :: Python :: 3.7
Classifier: Topic :: Scientific/Engineering :: Artificial Intelligence
Requires-Python: >=3.6.0
Requires-Dist: attrs (==19.3.0)
Requires-Dist: bs4 (==0.0.1)
Requires-Dist: jsonnet (==0.15.0)
Requires-Dist: lxml (==4.6.3)
Requires-Dist: datasets (==1.1.2)
Requires-Dist: nltk (>=3.5)
Requires-Dist: numexpr (==2.7.1)
Requires-Dist: numpy (==1.18.4)
Requires-Dist: pandas (==1.0.3)
Requires-Dist: python-Levenshtein (==0.12.0)
Requires-Dist: sacremoses (==0.0.43)
Requires-Dist: seqeval (==0.0.12)
Requires-Dist: scikit-learn (==0.22.2.post1)
Requires-Dist: scipy (==1.4.1)
Requires-Dist: sentencepiece (==0.1.91)
Requires-Dist: tokenizers (==0.10.1)
Requires-Dist: tqdm (==4.46.0)
Requires-Dist: transformers (==4.5.0)
Requires-Dist: torch (>=1.8.1)
Requires-Dist: torchvision (==0.9.1)
Provides-Extra: dev
Requires-Dist: pytest ; extra == 'dev'
Requires-Dist: pytest-cov ; extra == 'dev'
Requires-Dist: pre-commit ; extra == 'dev'
Requires-Dist: black (==19.10b0) ; extra == 'dev'
Requires-Dist: flake8-docstrings (==1.5.0) ; extra == 'dev'
Requires-Dist: flake8 (>=3.7.9) ; extra == 'dev'
Requires-Dist: mypy (==0.770) ; extra == 'dev'
Provides-Extra: docs
Requires-Dist: sphinx ; extra == 'docs'
Provides-Extra: quality
Requires-Dist: black (==19.10b0) ; extra == 'quality'
Requires-Dist: flake8-docstrings (==1.5.0) ; extra == 'quality'
Requires-Dist: flake8 (>=3.7.9) ; extra == 'quality'
Requires-Dist: mypy (==0.770) ; extra == 'quality'
Provides-Extra: testing
Requires-Dist: pytest ; extra == 'testing'
Requires-Dist: pytest-cov ; extra == 'testing'
Requires-Dist: pre-commit ; extra == 'testing'
